Metadata-Version: 1.1
Name: csv2athena-schema
Version: 0.1.1
Summary: A Python Script to build a athena create table from csv file
Home-page: https://github.com/yuokada/csv2athena_schema
Author: Yukihiro Okada
Author-email: callistoiv+pypi@gmail.com
License: Copyright 2019 Yukihiro Okada
